mastodon/Mastodon.py
mastodon/__init__.py
mastodon/streaming.py
Mastodonplus.py-1.5.5.4.dist-info/LICENSE
Mastodonplus.py-1.5.5.4.dist-info/METADATA
Mastodonplus.py-1.5.5.4.dist-info/WHEEL
Mastodonplus.py-1.5.5.4.dist-info/top_level.txt
Mastodonplus.py-1.5.5.4.dist-info/RECORD
